setup.py
bin/insteonic
insteonic/__init__.py
insteonic/commands.py
insteonic/devices.py
insteonic.egg-info/PKG-INFO
insteonic.egg-info/SOURCES.txt
insteonic.egg-info/dependency_links.txt
insteonic.egg-info/requires.txt
insteonic.egg-info/top_level.txt