Metadata-Version: 1.0
Name: insteonic
Version: 0.5
Summary: A Python command-line interface for Insteon's smartlinc controller
Home-page: http://packages.python.org/an_example_pypi_project
Author: Ryan Bagwell
Author-email: ryan@ryanbagwell.com
License: BSD
Keywords: Insteon automation
Platform: UNKNOWN
